Workbook

Sheet Start here
A1: MES business case template
A3: Business cases get approved faster when they show four things clearly:
A4: 1. What the problems cost today, in money (Baseline).
A5: 2. What will improve, by how much and when (Benefits).
A6: 3. Realistic costs and timeline, including your own people, not just licences and services (Costs).
A7: 4. How the risk is managed: a clear rollout plan across every site, with milestones and measures (Rollout).
A8: How to use it:
A9: Fill in Baseline with numbers finance will recognise. Set deliberately modest improvements on Benefits. Fill in every cost line, then read Cash flow.
A10: Make the case for every site as one programme: licences for all your sites, a template built on the first, and a clear plan for the rest.
A11: The example values describe a fictional mid-size site so you can see how it works. They are not a forecast. Replace them all.
A12: Every amount is in your own currency. Percentages are entered as percentages (35% not 0.35 is fine, Excel handles both).
A14: Key
A15: Yellow cell, blue text | B15: Your input. Replace the example values with your own.
A16: Black text | B16: Calculated. Leave these alone.
A17: Green text | B17: Pulled from another sheet.
A19: Shopfloor Matters · shopfloormatters.com · Free to use and adapt. General information, not professional advice.

Sheet Baseline
A1: Baseline: what the problems cost today
A2: Your site as it is now, for the lines or area in scope. Ask finance for revenue, margin and material cost. Measure the rest on the floor for a week if you can.
A4: Input | B4: Value | C4: Unit | D4: Where to get it
A5: Annual revenue from the lines in scope | B5: 25000000 | C5: currency / year | D5: Finance. Sales value of what these lines make.
A6: Contribution margin | B6: 0.35 | C6: % of revenue | D6: Finance. Revenue minus variable costs.
A7: Current OEE | B7: 0.55 | C7: % | D7: Measured, not estimated. Manual OEE usually flatters you.
A8: Share of extra output you could sell | B8: 0.5 | C8: % | D8: Sales. 100% if demand exceeds capacity, 0% if not.
A9: Annual material cost on these lines | B9: 11000000 | C9: currency / year | D9: Finance or ERP.
A10: Scrap and rework rate | B10: 0.04 | C10: % of material | D10: Quality. Scrap value ÷ material consumed.
A11: Hours a year spent on paper and re-keying | B11: 9000 | C11: hours / year | D11: Time it: forms, typing up, meeting prep, finding records.
A12: Loaded hourly rate | B12: 32 | C12: currency / hour | D12: HR or finance. Wage plus on-costs.
A13: Average inventory value (raw, WIP, finished) | B13: 4000000 | C13: currency | D13: Finance.
A14: Annual carrying cost of inventory | B14: 0.2 | C14: % of value | D14: Finance. Capital, storage, obsolescence. 15% to 25% is common.
A15: Annual maintenance spend on these lines | B15: 1200000 | C15: currency / year | D15: Maintenance or finance. Labour, contractors and spares.
A17: Cost of scrap and rework today | B17: =B9*B10 -> 440000
A18: Cost of paper and re-keying today | B18: =B11*B12 -> 288000
A19: Cost of carrying inventory today | B19: =B13*B14 -> 800000
A20: Value of one OEE point (the 1% question) | B20: =IF(B7>0,B5*(0.01/B7)*B8*B6,0) -> 79545.455

Sheet Benefits
A1: Benefits: what improves, and when
A2: Set improvements at the modest end. A board trusts a case that under-promises. The ramp sets how much of the full benefit you bank each year while the system beds in.
A4: Lever | B4: Improvement | C4: How it's measured | D4: Full-year benefit | E4: Note
A5: Higher OEE (points gained) | B5: 5 | C5: OEE points | D5: =Baseline!B20*B5 -> 397727.27 | E5: Uses the value of one OEE point from Baseline.
A6: Less scrap and rework | B6: 0.1 | C6: % cut in today's scrap cost | D6: =Baseline!B17*B6 -> 44000 | E6: A 10% cut in scrap is a modest target.
A7: Less paper and re-keying | B7: 0.5 | C7: % of today's paper hours removed | D7: =Baseline!B18*B7 -> 144000 | E7: Count only hours you'd really redeploy or stop paying for.
A8: Lower inventory | B8: 0.1 | C8: % cut in average inventory | D8: =Baseline!B19*B8 -> 80000 | E8: Carrying cost saved. The one-off cash release is not counted.
A9: Less reactive maintenance | B9: 0.05 | C9: % cut in maintenance spend | D9: =Baseline!B15*B9 -> 60000 | E9: From planned work replacing breakdowns.
A10: Total full-year benefit | D10: =SUM(D5:D9) -> 725727.27
B11: Year 1 | C11: Year 2 | D11: Year 3
A12: Benefit ramp | B12: 0.4 | C12: 0.8 | D12: 1
A13: Not counted here | B13: Quality escapes avoided, audit time, customer retention, less firefighting. Mention them, but keep them out of the numbers.

Sheet Costs
A1: Costs: every line, including your own people
A2: The internal team is the cost people forget. Name the people and the share of their time. Put contingency in on purpose, not as padding.
A4: Cost line | B4: Year 0 (setup) | C4: Year 1 | D4: Year 2 | E4: Year 3 | F4: Note
A5: Software subscription or licences | B5: 0 | C5: 90000 | D5: 90000 | E5: 90000 | F5: Subscription each year, or licences up front plus maintenance.
A6: Implementation services | B6: 250000 | C6: 30000 | D6: 0 | E6: 0 | F6: Partner or vendor services. Ask for the plan behind the number.
A7: Hardware and devices | B7: 80000 | C7: 10000 | D7: 10000 | E7: 10000 | F7: Tablets, terminals, scanners, printers, spares.
A8: Connectivity and infrastructure | B8: 60000 | C8: 0 | D8: 0 | E8: 0 | F8: Machine connectivity, network, Wi-Fi, edge.
A9: Internal team | B9: 150000 | C9: 80000 | D9: 40000 | E9: 40000 | F9: People × share of time × loaded cost. Project lead, super users, IT.
A10: Training | B10: 30000 | C10: 10000 | D10: 5000 | E10: 5000 | F10: Operators on every shift, super users, administrators.
A11: Running and support | B11: 0 | C11: 25000 | D11: 25000 | E11: 25000 | F11: Hosting, internal support, interface monitoring.
A12: Contingency | B12: =SUM(B5:B11)*$B$13 -> 85500 | C12: =SUM(C5:C11)*$B$13 -> 36750 | D12: =SUM(D5:D11)*$B$13 -> 25500 | E12: =SUM(E5:E11)*$B$13 -> 25500
A13: Contingency rate (applied to every year) | B13: 0.15
A14: Total cost | B14: =SUM(B5:B12) -> 655500 | C14: =SUM(C5:C12) -> 281750 | D14: =SUM(D5:D12) -> 195500 | E14: =SUM(E5:E12) -> 195500

Sheet Cash flow
A1: Cash flow, payback and ROI
A2: Three years, using the ramp on Benefits. Payback is the first year cumulative cash turns positive.
B4: Year 0 | C4: Year 1 | D4: Year 2 | E4: Year 3
A5: Benefit | B5: 0 | C5: =Benefits!$D$10*Benefits!B12 -> 290290.91 | D5: =Benefits!$D$10*Benefits!C12 -> 580581.82 | E5: =Benefits!$D$10*Benefits!D12 -> 725727.27
A6: Cost | B6: =-Costs!B14 -> -655500 | C6: =-Costs!C14 -> -281750 | D6: =-Costs!D14 -> -195500 | E6: =-Costs!E14 -> -195500
A7: Net cash flow | B7: =B5+B6 -> -655500 | C7: =C5+C6 -> 8540.9091 | D7: =D5+D6 -> 385081.82 | E7: =E5+E6 -> 530227.27
A8: Cumulative | B8: =B7 -> -655500 | C8: =B8+C7 -> -646959.09 | D8: =C8+D7 -> -261877.27 | E8: =D8+E7 -> 268350
A10: Three-year benefit | B10: =SUM(C5:E5) -> 1596600
A11: Three-year cost | B11: =-SUM(B6:E6) -> 1328250
A12: Three-year net benefit | B12: =B10-B11 -> 268350
A13: Three-year ROI | B13: =IF(B11>0,B12/B11,0) -> 0.20203275
A14: Payback | B14: =IF(C8>=0,"Year 1",IF(D8>=0,"Year 2",IF(E8>=0,"Year 3","After year 3"))) -> Year 3
A16: Cost of doing nothing, per year | B16: =Benefits!D10 -> 725727.27 | C16: Every year you wait, this is what stays on the table.

Sheet Rollout
A1: Rollout: how the risk is managed
A2: The section boards read most closely. The programme covers every site. Each stage has a scope, a measure and a milestone, so progress is visible all the way.
A4: Stage | B4: Scope | C4: Duration | D4: Success measure | E4: Milestone | F4: Owner
A5: 1. First site | B5: The whole site, starting with production and quality | C5: 6 to 9 months | D5: OEE up 3 points against baseline; scrap down 10% | E5: First site live on every shift | F5: Operations director
A6: 2. Template | B6: Standard processes, master data rules, KPIs and screens from the first site | C6: 2 to 3 months | D6: Template signed off by the centre of excellence | E6: Template ready for the next site | F6: Programme lead
A7: 3. Remaining sites | B7: Every other site, from the same template | C7: 4 to 6 months per site | D7: Go-live on time with under 10% local change; benefits on Benefits sheet reached | E7: Each site live on every shift | F7: Programme lead
