Workbook

Sheet How to use
A1: MES Matters social calendar
A3: Newsletter start date (first Tuesday) | B3: 46322
A5: How it works
A6: Every week features one MES Matters article. The newsletter sends it on Tuesday morning, and four posts per platform support it.
A7: Tuesday: the article post. LinkedIn link goes in the first comment, not the post.
A8: Monday, Thursday and Friday: supporting posts on the same theme, with no link.
A9: Write each post once, then adapt it for each platform using the LinkedIn, X and Instagram columns.
A10: Story posts are prompts: use your own real experience. Anonymise customers and companies.
A12: What to edit
A13: Change the start date above and every date in the calendar moves with it.
A14: In the Calendar tab, update Status and Notes as you go. Everything else is the plan.
A16: Status
A17: Planned: topic agreed, not written yet
A18: Drafted: copy written for all three platforms
... A26: Week 1, Tue: Hook 'Your operators don't need another app. They need fewer.' Status: Drafted. Notes: 'Carousel designed, LinkedIn copy approved.'

Sheet Calendar
A1: Week | B1: Date | C1: Day | D1: Featured article | E1: Pillar | F1: Post type | G1: Hook (first line) | H1: Key points | I1: LinkedIn | J1: X | K1: Instagram | L1: Link | M1: Post order | N1: Status | O1: Notes
A2: 1 | B2: ='Weekly overview'!$B$2+(-1) | C2: Mon | D2: Connected worker: why your operators need one app, not five | E2: Smart Factory & AI | F2: Stat or framework | G2: 72% of industrial organisations say frontline workforce issues have hurt their operational performance. | H2: • Source: LNS Research, 2023 (in the article) • The problem isn't effort. It's tools that don't talk to each other. Ask: how many screens does your operator touch in one shift? | I2: Image or document carousel. No link. | J2: Single post with the image. | K2: Carousel, 5–7 slides. | L2: No link (keeps reach up) | M2: 1 | N2: Drafted | O2: Copy in 'Social posts: weeks 1–4' doc; images on the carousels page
A3: 1 | B3: ='Weekly overview'!$B$2+(0) | C3: Tue | D3: Connected worker: why your operators need one app, not five | E3: Smart Factory & AI | F3: Article post | G3: Your operators don't need another app. They need fewer. | H3: • Connected worker solves real frontline problems: skills, checklists, handover, instructions • Bought standalone, it becomes app number five on the operator's screen • It belongs inside MES/MOM, on the same data as production • Article: what it is, why now, and the word of caution | I3: Text post, 150–250 words. Article link in the FIRST COMMENT. | J3: Thread, 5–7 posts. Link in the last post. | K3: Carousel, 7–9 slides. 'Link in bio' on the last slide. | L3: https://www.mesmatters.com/post/connected-worker-one-app-not-five | M3: 2 | N3: Drafted | O3: Copy in 'Social posts: weeks 1–4' doc; images on the carousels page
A4: 1 | B4: ='Weekly overview'!$B$2+(2) | C4: Thu | D4: Connected worker: why your operators need one app, not five | E4: Smart Factory & AI | F4: Question / poll | G4: How many different apps does an operator in your factory use in a single shift? | H4: • Poll options: 1–2 / 3–4 / 5+ / I've never counted • Follow up in comments with why it matters: every switch loses context | I4: LinkedIn poll (1 week). Reply to comments. | J4: Poll. | K4: Story poll, plus a quote graphic in the feed. | L4: No link (keeps reach up) | M4: 3 | N4: Drafted | O4: Copy in 'Social posts: weeks 1–4' doc; images on the carousels page
A5: 1 | B5: ='Weekly overview'!$B$2+(3) | C5: Fri | D5: Connected worker: why your operators need one app, not five | E5: Smart Factory & AI | F5: Contrarian take | G5: A connected worker platform that duplicates your MES isn't digital transformation. It's a new silo with a nicer UI. | H5: • Two systems, two versions of the truth about the same shift • Integration costs land later, and they land on IT. Better question: what does the operator need on one screen? | I5: Short text post, 50–120 words. No link. | J5: Single post. | K5: Carousel: the take on slide 1, the reasoning over 3–4 slides. | L5: No link (keeps reach up) | M5: 4 | N5: Drafted | O5: Copy in 'Social posts: weeks 1–4' doc; images on the carousels page
A6: 2 | B6: ='Weekly overview'!$B$3+(-1) | C6: Mon | D6: What is a smart factory? No version number required | E6: Smart Factory & AI | F6: Myth vs reality | G6: Myth: a smart factory is full of robots and empty of people. | H6: • Reality: the smartest factories I've seen are full of people making better decisions • Automation matters, but data and process matter first. Carousel: 4 myths vs reality | I6: Text post or document carousel. No link. | J6: Single post. | K6: Carousel: myth slide, reality slide. | L6: No link (keeps reach up) | M6: 1 | N6: Drafted | O6: Copy in 'Social posts: weeks 1–4' doc; images on the carousels page
A7: 2 | B7: ='Weekly overview'!$B$3+(0) | C7: Tue | D7: What is a smart factory? No version number required | E7: Smart Factory & AI | F7: Article post | G7: A smart factory doesn't need a version number. | H7: • It's not Industry 6.0 or science fiction • It's people, processes and technology working together on good data • Five things define it, and none of them is a robot • It doesn't reduce complexity. It helps you manage it | I7: Text post, 150–250 words. Article link in the FIRST COMMENT. | J7: Thread, 5–7 posts. Link in the last post. | K7: Carousel, 7–9 slides. 'Link in bio' on the last slide. | L7: https://www.mesmatters.com/post/what-is-a-smart-factory | M7: 2 | N7: Drafted | O7: Copy in 'Social posts: weeks 1–4' doc; images on the carousels page
A8: 2 | B8: ='Weekly overview'!$B$3+(2) | C8: Thu | D8: What is a smart factory? No version number required | E8: Smart Factory & AI | F8: Stat or framework | G8: Deloitte asked 600 large manufacturers what smart manufacturing delivered. The headline: production output up 10–20% on average. | H8: • Deloitte 2025 Smart Manufacturing Survey (in the article) • These are averages from large companies, self-reported. The point: the returns are real when the basics are in place | I8: Image or document carousel. No link. | J8: Single post with the image. | K8: Carousel, 5–7 slides. | L8: No link (keeps reach up) | M8: 3 | N8: Drafted | O8: Copy in 'Social posts: weeks 1–4' doc; images on the carousels page
A9: 2 | B9: ='Weekly overview'!$B$3+(3) | C9: Fri | D9: What is a smart factory? No version number required | E9: Smart Factory & AI | F9: Story (your experience) | G9: Story prompt: the moment you realised a factory was 'smart' (or wasn't). | H9: • Your experience: a visit, a project, a conversation on the shopfloor • What gave it away? Data on screens, or people chasing paper?. End: what would you look for on a factory tour? | I9: Story post, 150–250 words, from your own experience. No link. | J9: Short thread, 3–4 posts. | K9: Reel: 30–45 sec talking to camera. | L9: No link (keeps reach up) | M9: 4 | N9: Drafted | O9: Copy in 'Social posts: weeks 1–4' doc; images on the carousels page
A10: 3 | B10: ='Weekly overview'!$B$4+(-1) | C10: Mon | D10: AI, ML and GenAI on the shopfloor: what each one actually does | E10: Smart Factory & AI | F10: Analogy | G10: Machine learning is older than you think. SPC has been spotting drift on production lines for decades. | H10: • Learn what normal looks like, then flag what isn't • That's the core idea behind a lot of 'AI' being sold today. Point: don't let the label distract you from the data | I10: Short text post, 50–120 words. No link. | J10: Single post. | K10: Quote graphic. | L10: No link (keeps reach up) | M10: 1 | N10: Drafted | O10: Copy in 'Social posts: weeks 1–4' doc; images on the carousels page
A11: 3 | B11: ='Weekly overview'!$B$4+(0) | C11: Tue | D11: AI, ML and GenAI on the shopfloor: what each one actually does | E11: Smart Factory & AI | F11: Article post | G11: AI, ML and GenAI are not the same thing. Using them interchangeably costs money. | H11: • Machine learning: predicting outcomes from your operational data • Generative AI: creating text, summaries and answers • Agentic AI: systems that take actions • All of them need the same thing first: clean, contextualised data | I11: Text post, 150–250 words. Article link in the FIRST COMMENT. | J11: Thread, 5–7 posts. Link in the last post. | K11: Carousel, 7–9 slides. 'Link in bio' on the last slide. | L11: https://www.mesmatters.com/post/ai-ml-genai-on-the-shopfloor | M11: 2 | N11: Drafted | O11: Copy in 'Social posts: weeks 1–4' doc; images on the carousels page
A12: 3 | B12: ='Weekly overview'!$B$4+(2) | C12: Thu | D12: AI, ML and GenAI on the shopfloor: what each one actually does | E12: Smart Factory & AI | F12: Question / poll | G12: Which AI use case would you fund first in your factory? | H12: • Poll: predictive maintenance / predictive quality / GenAI assistant for operators / natural-language reporting • Comment with what's stopping you | I12: LinkedIn poll (1 week). Reply to comments. | J12: Poll. | K12: Story poll, plus a quote graphic in the feed. | L12: No link (keeps reach up) | M12: 3 | N12: Drafted | O12: Copy in 'Social posts: weeks 1–4' doc; images on the carousels page
A13: 3 | B13: ='Weekly overview'!$B$4+(3) | C13: Fri | D13: AI, ML and GenAI on the shopfloor: what each one actually does | E13: Smart Factory & AI | F13: Contrarian take | G13: If your shopfloor data is typed in at the end of the shift, your AI project is a very expensive guess. | H13: • Models learn from what you feed them • Estimates in, confident-looking nonsense out. Fix the data capture first, then talk about models | I13: Short text post, 50–120 words. No link. | J13: Single post. | K13: Carousel: the take on slide 1, the reasoning over 3–4 slides. | L13: No link (keeps reach up) | M13: 4 | N13: Drafted | O13: Copy in 'Social posts: weeks 1–4' doc; images on the carousels page
A14: 4 | B14: ='Weekly overview'!$B$5+(-1) | C14: Mon | D14: The smart manufacturing maturity model: you can't skip a level | E14: Smart Factory & AI | F14: Checklist | G14: Four questions to find your factory's real maturity level. | H14: • Is production data captured automatically or typed in later? • Do production, quality and maintenance use the same data? • Can you trace a lot in minutes? • Do decisions use real-time data or last week's report? • Carousel: one slide per level | I14: Document carousel (PDF), one item per page. | J14: Thread, one item per post. | K14: Carousel, one item per slide. | L14: No link (keeps reach up) | M14: 1 | N14: Drafted | O14: Copy in 'Social posts: weeks 1–4' doc; images on the carousels page
A15: 4 | B15: ='Weekly overview'!$B$5+(0) | C15: Tue | D15: The smart manufacturing maturity model: you can't skip a level | E15: Smart Factory & AI | F15: Article post | G15: You can't skip a level of smart manufacturing maturity. Most factories are trying to. | H15: • Five levels from paper-driven to AI-enabled • Most factories sit between levels 1 and 3 • AI starts paying back around level 4, not before • Use the model to decide your next step, not your end state | I15: Text post, 150–250 words. Article link in the FIRST COMMENT. | J15: Thread, 5–7 posts. Link in the last post. | K15: Carousel, 7–9 slides. 'Link in bio' on the last slide. | L15: https://www.mesmatters.com/post/smart-manufacturing-maturity-model | M15: 2 | N15: Drafted | O15: Copy in 'Social posts: weeks 1–4' doc; images on the carousels page
A16: 4 | B16: ='Weekly overview'!$B$5+(2) | C16: Thu | D16: The smart manufacturing maturity model: you can't skip a level | E16: Smart Factory & AI | F16: Question / poll | G16: Be honest: what maturity level is your factory at today? | H16: • Poll: 1 Paper / 2 Spreadsheets / 3 Systems in silos / 4 Joined-up data • Comment: what's blocking the next step? | I16: LinkedIn poll (1 week). Reply to comments. | J16: Poll. | K16: Story poll, plus a quote graphic in the feed. | L16: No link (keeps reach up) | M16: 3 | N16: Drafted | O16: Copy in 'Social posts: weeks 1–4' doc; images on the carousels page
A17: 4 | B17: ='Weekly overview'!$B$5+(3) | C17: Fri | D17: The smart manufacturing maturity model: you can't skip a level | E17: Smart Factory & AI | F17: Contrarian take | G17: Buying AI before you've fixed your data is like fitting a turbo to a car with flat tyres. | H17: • Each level builds on the one before • Skipping ahead means paying twice. Where would your money go further this year? | I17: Short text post, 50–120 words. No link. | J17: Single post. | K17: Carousel: the take on slide 1, the reasoning over 3–4 slides. | L17: No link (keeps reach up) | M17: 4 | N17: Drafted | O17: Copy in 'Social posts: weeks 1–4' doc; images on the carousels page
A18: 5 | B18: ='Weekly overview'!$B$6+(-1) | C18: Mon | D18: PLM, ERP and MES: where the digital thread actually runs | E18: Foundations | F18: Stat or framework | G18: The digital thread in one picture: PLM → ERP → MES/MOM → service, and back again. | H18: • Graphic: who owns what at each step • The return path is the one most companies forget. Carousel version for Instagram | I18: Image or document carousel. No link. | J18: Single post with the image. | K18: Carousel, 5–7 slides. | L18: No link (keeps reach up) | M18: 1 | N18: Planned
A19: 5 | B19: ='Weekly overview'!$B$6+(0) | C19: Tue | D19: PLM, ERP and MES: where the digital thread actually runs | E19: Foundations | F19: Article post | G19: Everyone talks about the digital thread. Few can tell you where it actually runs. | H19: • PLM owns the product definition • ERP owns orders, cost and supply • MES/MOM owns how it's actually made, and the as-built record • ERP usually sits in the middle, and the hard part is engineering changes | I19: Text post, 150–250 words. Article link in the FIRST COMMENT. | J19: Thread, 5–7 posts. Link in the last post. | K19: Carousel, 7–9 slides. 'Link in bio' on the last slide. | L19: https://www.mesmatters.com/post/plm-erp-mes-digital-thread | M19: 2 | N19: Planned
A20: 5 | B20: ='Weekly overview'!$B$6+(2) | C20: Thu | D20: PLM, ERP and MES: where the digital thread actually runs | E20: Foundations | F20: Question / poll | G20: Does engineering change data reach your operators before or after the first wrong part? | H20: • Poll: before / same day / after / we find out from quality • Comment: how do changes reach your line today? | I20: LinkedIn poll (1 week). Reply to comments. | J20: Poll. | K20: Story poll, plus a quote graphic in the feed. | L20: No link (keeps reach up) | M20: 3 | N20: Planned
A21: 5 | B21: ='Weekly overview'!$B$6+(3) | C21: Fri | D21: PLM, ERP and MES: where the digital thread actually runs | E21: Foundations | F21: Contrarian take | G21: A direct PLM to MES link isn't always the answer. Sometimes ERP in the middle is exactly right. | H21: • Direct links make sense for complex, fast-changing products • For most, ERP holds effectivity and keeps everyone aligned. Choose based on change frequency, not fashion | I21: Short text post, 50–120 words. No link. | J21: Single post. | K21: Carousel: the take on slide 1, the reasoning over 3–4 slides. | L21: No link (keeps reach up) | M21: 4 | N21: Planned
A22: 6 | B22: ='Weekly overview'!$B$7+(-1) | C22: Mon | D22: Shift handover is a process. Treat it like one. | E22: Smart Factory & AI | F22: Story (your experience) | G22: Story prompt: the worst handover you've ever seen, and what it cost. | H22: • Your experience: a missed issue, a repeated fault, a safety near-miss • What information was missing?. End: what does good look like in your plant? | I22: Story post, 150–250 words, from your own experience. No link. | J22: Short thread, 3–4 posts. | K22: Reel: 30–45 sec talking to camera. | L22: No link (keeps reach up) | M22: 1 | N22: Planned
A23: 6 | B23: ='Weekly overview'!$B$7+(0) | C23: Tue | D23: Shift handover is a process. Treat it like one. | E23: Smart Factory & AI | F23: Article post | G23: Shift handover is a process. Most factories treat it like a chat at the door. | H23: • Verbal handovers lose detail and the next crew starts blind • A good handover answers a handful of specific questions • Build it from real data, structured, not just typed • Start this week, even before you change systems | I23: Text post, 150–250 words. Article link in the FIRST COMMENT. | J23: Thread, 5–7 posts. Link in the last post. | K23: Carousel, 7–9 slides. 'Link in bio' on the last slide. | L23: https://www.mesmatters.com/post/digital-shift-handover | M23: 2 | N23: Planned
A24: 6 | B24: ='Weekly overview'!$B$7+(2) | C24: Thu | D24: Shift handover is a process. Treat it like one. | E24: Smart Factory & AI | F24: Checklist | G24: Four questions every shift handover should answer. | H24: • What ran, and how did it perform? • What stopped, and is it fixed? • Any quality holds or open issues? • What's planned, and what's at risk? • Carousel: one question per slide | I24: Document carousel (PDF), one item per page. | J24: Thread, one item per post. | K24: Carousel, one item per slide. | L24: No link (keeps reach up) | M24: 3 | N24: Planned
A25: 6 | B25: ='Weekly overview'!$B$7+(3) | C25: Fri | D25: Shift handover is a process. Treat it like one. | E25: Smart Factory & AI | F25: Contrarian take | G25: A digital handover form that copies the paper one isn't a digital handover. | H25: • If people still retype what the system already knows, nothing improved • Pre-fill from production data, then add what only people know. Structure beats free text, every time | I25: Short text post, 50–120 words. No link. | J25: Single post. | K25: Carousel: the take on slide 1, the reasoning over 3–4 slides. | L25: No link (keeps reach up) | M25: 4 | N25: Planned
A26: 7 | B26: ='Weekly overview'!$B$8+(-1) | C26: Mon | D26: The smart factory tech stack, system by system | E26: Foundations | F26: Stat or framework | G26: The smart factory tech stack on one page. | H26: • Graphic: four layers, systems in each, arrows between them • Save it for your next architecture review. Carousel: one layer per slide | I26: Image or document carousel. No link. | J26: Single post with the image. | K26: Carousel, 5–7 slides. | L26: No link (keeps reach up) | M26: 1 | N26: Planned
A27: 7 | B27: ='Weekly overview'!$B$8+(0) | C27: Tue | D27: The smart factory tech stack, system by system | E27: Foundations | F27: Article post | G27: ERP, PLM, APS, MES, WMS, CMMS, LIMS, historians. Who does what? | H27: • The enterprise layer, the operations layer, the connectivity layer and the data layer • Where the boundaries sit, and why overlaps cost money • Questions to ask about every system you own • The article walks through it system by system | I27: Text post, 150–250 words. Article link in the FIRST COMMENT. | J27: Thread, 5–7 posts. Link in the last post. | K27: Carousel, 7–9 slides. 'Link in bio' on the last slide. | L27: https://www.mesmatters.com/post/smart-factory-tech-stack | M27: 2 | N27: Planned
A28: 7 | B28: ='Weekly overview'!$B$8+(2) | C28: Thu | D28: The smart factory tech stack, system by system | E28: Foundations | F28: Question / poll | G28: Which boundary causes the most arguments in your organisation? | H28: • Poll: ERP vs MES / MES vs WMS / MES vs CMMS / MES vs QMS • Comment with your war story | I28: LinkedIn poll (1 week). Reply to comments. | J28: Poll. | K28: Story poll, plus a quote graphic in the feed. | L28: No link (keeps reach up) | M28: 3 | N28: Planned
A29: 7 | B29: ='Weekly overview'!$B$8+(3) | C29: Fri | D29: The smart factory tech stack, system by system | E29: Foundations | F29: Contrarian take | G29: You don't need every acronym in the stack. You need clear ownership of every piece of data. | H29: • Two systems owning the same data is where projects go wrong • Decide the system of record before you buy. Fewer systems, clearer boundaries | I29: Short text post, 50–120 words. No link. | J29: Single post. | K29: Carousel: the take on slide 1, the reasoning over 3–4 slides. | L29: No link (keeps reach up) | M29: 4 | N29: Planned
A30: 8 | B30: ='Weekly overview'!$B$9+(-1) | C30: Mon | D30: MES vs MOM: why the difference matters when you buy | E30: Foundations | F30: Analogy | G30: MES is one instrument. MOM is the orchestra. | H30: • Production on its own can sound great • But quality, inventory and maintenance have to play from the same score. Separate systems per pillar means four conductors | I30: Short text post, 50–120 words. No link. | J30: Single post. | K30: Quote graphic. | L30: No link (keeps reach up) | M30: 1 | N30: Planned
A31: 8 | B31: ='Weekly overview'!$B$9+(0) | C31: Tue | D31: MES vs MOM: why the difference matters when you buy | E31: Foundations | F31: Article post | G31: MES and MOM are used interchangeably. They shouldn't be, especially when you're buying. | H31: • MES is production execution: orders, counts, scrap, downtime, OEE • MOM covers production, quality, inventory and maintenance • The value is everyone working on the same data • The risk: a different system per pillar, stitched together | I31: Text post, 150–250 words. Article link in the FIRST COMMENT. | J31: Thread, 5–7 posts. Link in the last post. | K31: Carousel, 7–9 slides. 'Link in bio' on the last slide. | L31: https://www.mesmatters.com/post/mes-vs-mom | M31: 2 | N31: Planned
A32: 8 | B32: ='Weekly overview'!$B$9+(2) | C32: Thu | D32: MES vs MOM: why the difference matters when you buy | E32: Foundations | F32: Question / poll | G32: How many systems run production, quality, inventory and maintenance in your factory? | H32: • Poll: 1 / 2 / 3–4 / More than 4 • Comment: where does data fall between the cracks? | I32: LinkedIn poll (1 week). Reply to comments. | J32: Poll. | K32: Story poll, plus a quote graphic in the feed. | L32: No link (keeps reach up) | M32: 3 | N32: Planned
A33: 8 | B33: ='Weekly overview'!$B$9+(3) | C33: Fri | D33: MES vs MOM: why the difference matters when you buy | E33: Foundations | F33: Checklist | G33: Four questions to ask any vendor who says they 'do MOM'. | H33: • Which pillars are native, and which are partner products? • Is it one data model or several integrated ones? • Can a quality hold stop a production order instantly? • Show me, don't tell me | I33: Document carousel (PDF), one item per page. | J33: Thread, one item per post. | K33: Carousel, one item per slide. | L33: No link (keeps reach up) | M33: 4 | N33: Planned
A34: 9 | B34: ='Weekly overview'!$B$10+(-1) | C34: Mon | D34: EBOM, MBOM, as-built: who owns the BOM at each stage | E34: Foundations | F34: Stat or framework | G34: EBOM → MBOM → order BOM → as-built. One graphic, four owners. | H34: • Graphic: the BOM's journey from engineering to shipment • Label the system of record at each stage. Carousel for Instagram | I34: Image or document carousel. No link. | J34: Single post with the image. | K34: Carousel, 5–7 slides. | L34: No link (keeps reach up) | M34: 1 | N34: Planned
A35: 9 | B35: ='Weekly overview'!$B$10+(0) | C35: Tue | D35: EBOM, MBOM, as-built: who owns the BOM at each stage | E35: Foundations | F35: Article post | G35: A bill of materials changes shape four times before a product ships. Who owns it at each stage? | H35: • EBOM in PLM, MBOM in ERP, order BOM for the job, as-built in MES/MOM • Problems start where ownership is unclear • The as-built record is the one you'll need in a recall • Article: who owns what, and where it goes wrong | I35: Text post, 150–250 words. Article link in the FIRST COMMENT. | J35: Thread, 5–7 posts. Link in the last post. | K35: Carousel, 7–9 slides. 'Link in bio' on the last slide. | L35: https://www.mesmatters.com/post/ebom-mbom-as-built | M35: 2 | N35: Planned
A36: 9 | B36: ='Weekly overview'!$B$10+(2) | C36: Thu | D36: EBOM, MBOM, as-built: who owns the BOM at each stage | E36: Foundations | F36: Question / poll | G36: Where does BOM data go wrong most often in your business? | H36: • Poll: EBOM to MBOM / MBOM to order / order to as-built / we don't capture as-built • Comment with an example | I36: LinkedIn poll (1 week). Reply to comments. | J36: Poll. | K36: Story poll, plus a quote graphic in the feed. | L36: No link (keeps reach up) | M36: 3 | N36: Planned
A37: 9 | B37: ='Weekly overview'!$B$10+(3) | C37: Fri | D37: EBOM, MBOM, as-built: who owns the BOM at each stage | E37: Foundations | F37: Contrarian take | G37: If you can't produce an as-built record in minutes, you don't have traceability. You have a parts list. | H37: • What was planned and what was built are different things • Substitutions, rework and serial numbers live in MES/MOM. Ask: how long would a recall investigation take today? | I37: Short text post, 50–120 words. No link. | J37: Single post. | K37: Carousel: the take on slide 1, the reasoning over 3–4 slides. | L37: No link (keeps reach up) | M37: 4 | N37: Planned
A38: 10 | B38: ='Weekly overview'!$B$11+(-1) | C38: Mon | D38: Raw machine data is worthless. Context is what makes it useful | E38: Smart Factory & AI | F38: Analogy | G38: A machine signal without context is like a heart rate without knowing if someone is sleeping or sprinting. | H38: • Same number, completely different meaning • MES/MOM adds the 'what was happening' around every signal. That's the difference between data and a decision | I38: Short text post, 50–120 words. No link. | J38: Single post. | K38: Quote graphic. | L38: No link (keeps reach up) | M38: 1 | N38: Planned
A39: 10 | B39: ='Weekly overview'!$B$11+(0) | C39: Tue | D39: Raw machine data is worthless. Context is what makes it useful | E39: Smart Factory & AI | F39: Article post | G39: Raw machine data is worthless. Context is what makes it useful. | H39: • A signal that says 'stopped' tells you nothing on its own • Order, product, operator, reason and tool turn it into information • Point solutions lose that context at every boundary • Context is also what AI really needs | I39: Text post, 150–250 words. Article link in the FIRST COMMENT. | J39: Thread, 5–7 posts. Link in the last post. | K39: Carousel, 7–9 slides. 'Link in bio' on the last slide. | L39: https://www.mesmatters.com/post/contextualised-manufacturing-data | M39: 2 | N39: Planned
A40: 10 | B40: ='Weekly overview'!$B$11+(2) | C40: Thu | D40: Raw machine data is worthless. Context is what makes it useful | E40: Smart Factory & AI | F40: Stat or framework | G40: From signal to decision in four steps. | H40: • Signal: Machine 3 stopped • Context: order 4471, tool T-114, night shift • Insight: the same tool causes most rejects • Decision: replace the tool. Carousel walk-through | I40: Image or document carousel. No link. | J40: Single post with the image. | K40: Carousel, 5–7 slides. | L40: No link (keeps reach up) | M40: 3 | N40: Planned
A41: 10 | B41: ='Weekly overview'!$B$11+(3) | C41: Fri | D41: Raw machine data is worthless. Context is what makes it useful | E41: Smart Factory & AI | F41: Question / poll | G41: Where does most of your shopfloor data lose its context? | H41: • Poll: machine to historian / historian to reports / between departments / it never had any • Comment: what's the fix? | I41: LinkedIn poll (1 week). Reply to comments. | J41: Poll. | K41: Story poll, plus a quote graphic in the feed. | L41: No link (keeps reach up) | M41: 4 | N41: Planned
A42: 11 | B42: ='Weekly overview'!$B$12+(-1) | C42: Mon | D42: How to build an MES business case leadership will sign | E42: Implementation | F42: Question / poll | G42: What's the real blocker on your MES business case? | H42: • Poll: no data to prove ROI / leadership doesn't see urgency / investment too big / tried before and failed • Comment: what would change their mind? | I42: LinkedIn poll (1 week). Reply to comments. | J42: Poll. | K42: Story poll, plus a quote graphic in the feed. | L42: No link (keeps reach up) | M42: 1 | N42: Planned
A43: 11 | B43: ='Weekly overview'!$B$12+(0) | C43: Tue | D43: How to build an MES business case leadership will sign | E43: Implementation | F43: Article post | G43: Your factory runs on paper and Excel. Your leadership hasn't approved the fix. Here's why. | H43: • Business cases fail when they talk features, not impact • Structure it around cost, risk and the cost of doing nothing • Use the 1% question • Don't promise everything on day one | I43: Text post, 150–250 words. Article link in the FIRST COMMENT. | J43: Thread, 5–7 posts. Link in the last post. | K43: Carousel, 7–9 slides. 'Link in bio' on the last slide. | L43: https://www.mesmatters.com/post/mes-business-case | M43: 2 | N43: Planned
A44: 11 | B44: ='Weekly overview'!$B$12+(2) | C44: Thu | D44: How to build an MES business case leadership will sign | E44: Implementation | F44: Stat or framework | G44: The 1% question: what would a 1% OEE improvement on your bottleneck be worth? | H44: • Work it out: extra output, less overtime, deferred capex • For most manufacturers it's a big number. Put that number on slide one | I44: Image or document carousel. No link. | J44: Single post with the image. | K44: Carousel, 5–7 slides. | L44: No link (keeps reach up) | M44: 3 | N44: Planned
A45: 11 | B45: ='Weekly overview'!$B$12+(3) | C45: Fri | D45: How to build an MES business case leadership will sign | E45: Implementation | F45: Contrarian take | G45: 'We can't prove the ROI' usually means 'we haven't measured what bad looks like today'. | H45: • Baseline your scrap, downtime and admin hours first • The cost of doing nothing is a number too. Build the case from your data, not a vendor's brochure | I45: Short text post, 50–120 words. No link. | J45: Single post. | K45: Carousel: the take on slide 1, the reasoning over 3–4 slides. | L45: No link (keeps reach up) | M45: 4 | N45: Planned
A46: 12 | B46: ='Weekly overview'!$B$13+(-1) | C46: Mon | D46: The biggest barriers to MES success in food manufacturing | E46: Implementation | F46: Story (your experience) | G46: Story prompt: a food or beverage project that stumbled, and why. | H46: • Your experience: what went wrong first, people, scope or data? • What would you do differently?. End: advice for anyone starting now | I46: Story post, 150–250 words, from your own experience. No link. | J46: Short thread, 3–4 posts. | K46: Reel: 30–45 sec talking to camera. | L46: No link (keeps reach up) | M46: 1 | N46: Planned
A47: 12 | B47: ='Weekly overview'!$B$13+(0) | C47: Tue | D47: The biggest barriers to MES success in food manufacturing | E47: Implementation | F47: Article post | G47: Food manufacturers rarely fail at MES because of the technology. | H47: • People are the biggest risk, not software • Starting too big, too fast • Underestimating the master data foundation • Choosing a platform built for a different industry | I47: Text post, 150–250 words. Article link in the FIRST COMMENT. | J47: Thread, 5–7 posts. Link in the last post. | K47: Carousel, 7–9 slides. 'Link in bio' on the last slide. | L47: https://www.mesmatters.com/post/food-manufacturing-mes-barriers | M47: 2 | N47: Planned
A48: 12 | B48: ='Weekly overview'!$B$13+(2) | C48: Thu | D48: The biggest barriers to MES success in food manufacturing | E48: Implementation | F48: Checklist | G48: Four questions for any food manufacturer starting an MES project. | H48: • Who on the shopfloor owns adoption? • Is your first scope one line or the whole site? • Are recipes and specs clean enough to digitise? • Does the platform handle yield, give-away and shelf life? | I48: Document carousel (PDF), one item per page. | J48: Thread, one item per post. | K48: Carousel, one item per slide. | L48: No link (keeps reach up) | M48: 3 | N48: Planned
A49: 12 | B49: ='Weekly overview'!$B$13+(3) | C49: Fri | D49: The biggest barriers to MES success in food manufacturing | E49: Implementation | F49: Question / poll | G49: What's the biggest challenge on your food production lines? | H49: • Poll: yield and give-away / traceability / labour and skills / compliance paperwork • Comment with your top one | I49: LinkedIn poll (1 week). Reply to comments. | J49: Poll. | K49: Story poll, plus a quote graphic in the feed. | L49: No link (keeps reach up) | M49: 4 | N49: Planned
A50: 13 | B50: ='Weekly overview'!$B$14+(-1) | C50: Mon | D50: From CPQ to the shopfloor: building what the customer actually configured | E50: Foundations | F50: Stat or framework | G50: CPQ → ERP → (PLM) → MES/MOM: how a configuration reaches the line. | H50: • Graphic: configure-to-order vs engineer-to-order paths • Where each system adds detail. Carousel | I50: Image or document carousel. No link. | J50: Single post with the image. | K50: Carousel, 5–7 slides. | L50: No link (keeps reach up) | M50: 1 | N50: Planned
A51: 13 | B51: ='Weekly overview'!$B$14+(0) | C51: Tue | D51: From CPQ to the shopfloor: building what the customer actually configured | E51: Foundations | F51: Article post | G51: The customer configured it in CPQ. Does your operator know what to build? | H51: • Configured products start in CPQ and flow through ERP • Engineer-to-order adds PLM to the mix • The operator needs the configuration, not a generic routing • Close the loop so as-built matches what was sold | I51: Text post, 150–250 words. Article link in the FIRST COMMENT. | J51: Thread, 5–7 posts. Link in the last post. | K51: Carousel, 7–9 slides. 'Link in bio' on the last slide. | L51: https://www.mesmatters.com/post/cpq-to-shopfloor | M51: 2 | N51: Planned
A52: 13 | B52: ='Weekly overview'!$B$14+(2) | C52: Thu | D52: From CPQ to the shopfloor: building what the customer actually configured | E52: Foundations | F52: Question / poll | G52: How do operators see order-specific options in your factory? | H52: • Poll: on screen per order / printed traveller / generic instruction + notes / they ask someone • Comment with your approach | I52: LinkedIn poll (1 week). Reply to comments. | J52: Poll. | K52: Story poll, plus a quote graphic in the feed. | L52: No link (keeps reach up) | M52: 3 | N52: Planned
A53: 13 | B53: ='Weekly overview'!$B$14+(3) | C53: Fri | D53: From CPQ to the shopfloor: building what the customer actually configured | E53: Foundations | F53: Contrarian take | G53: If your operators work from a generic routing on a configured product, the configuration ends at the sales team. | H53: • Errors creep in between quote and build • Show the operator exactly what this order needs. Error-proof the options, not just the parts | I53: Short text post, 50–120 words. No link. | J53: Single post. | K53: Carousel: the take on slide 1, the reasoning over 3–4 slides. | L53: No link (keeps reach up) | M53: 4 | N53: Planned
A54: 14 | B54: ='Weekly overview'!$B$15+(-1) | C54: Mon | D54: Skills you can enforce, not just record | E54: Smart Factory & AI | F54: Question / poll | G54: How does your factory stop an untrained operator starting a job? | H54: • Poll: the system blocks it / supervisor checks / we trust people / we find out at audit • Comment: be honest | I54: LinkedIn poll (1 week). Reply to comments. | J54: Poll. | K54: Story poll, plus a quote graphic in the feed. | L54: No link (keeps reach up) | M54: 1 | N54: Planned
A55: 14 | B55: ='Weekly overview'!$B$15+(0) | C55: Tue | D55: Skills you can enforce, not just record | E55: Smart Factory & AI | F55: Article post | G55: Your skills matrix lives in a spreadsheet nobody checks at the point of work. | H55: • Recording skills is not enforcing them • The system should stop the wrong person starting the wrong job • Expiring certifications need warnings, not audits • It belongs inside MES/MOM, where the work happens | I55: Text post, 150–250 words. Article link in the FIRST COMMENT. | J55: Thread, 5–7 posts. Link in the last post. | K55: Carousel, 7–9 slides. 'Link in bio' on the last slide. | L55: https://www.mesmatters.com/post/skills-enforcement-shopfloor | M55: 2 | N55: Planned
A56: 14 | B56: ='Weekly overview'!$B$15+(2) | C56: Thu | D56: Skills you can enforce, not just record | E56: Smart Factory & AI | F56: Contrarian take | G56: A skills matrix that can't block a job is a report, not a control. | H56: • Audits find the gaps months later • Enforcement at the point of work prevents the defect. Simple test: try logging in to a job you're not trained for | I56: Short text post, 50–120 words. No link. | J56: Single post. | K56: Carousel: the take on slide 1, the reasoning over 3–4 slides. | L56: No link (keeps reach up) | M56: 3 | N56: Planned
A57: 14 | B57: ='Weekly overview'!$B$15+(3) | C57: Fri | D57: Skills you can enforce, not just record | E57: Smart Factory & AI | F57: Story (your experience) | G57: Story prompt: a quality or safety issue that came down to someone doing a job they weren't trained for. | H57: • Your experience, anonymised • What would a system check have changed?. End: how do you handle skills today? | I57: Story post, 150–250 words, from your own experience. No link. | J57: Short thread, 3–4 posts. | K57: Reel: 30–45 sec talking to camera. | L57: No link (keeps reach up) | M57: 4 | N57: Planned
A58: 15 | B58: ='Weekly overview'!$B$16+(-1) | C58: Mon | D58: Practical GenAI for the shopfloor: four uses that save time today | E58: Smart Factory & AI | F58: Contrarian take | G58: GenAI won't fix a factory that can't tell you what ran last night. | H58: • It summarises and explains. It doesn't invent missing data • Garbage in, beautifully written garbage out | I58: Short text post, 50–120 words. No link. | J58: Single post. | K58: Carousel: the take on slide 1, the reasoning over 3–4 slides. | L58: No link (keeps reach up) | M58: 1 | N58: Planned
A59: 15 | B59: ='Weekly overview'!$B$16+(0) | C59: Tue | D59: Practical GenAI for the shopfloor: four uses that save time today | E59: Smart Factory & AI | F59: Article post | G59: Forget the hype. Here are four ways GenAI saves time in factories today. | H59: • Asking questions of your data in plain English • Helping configure systems faster • A knowledge assistant on every screen • Shift summaries written for you, if the data underneath is good | I59: Text post, 150–250 words. Article link in the FIRST COMMENT. | J59: Thread, 5–7 posts. Link in the last post. | K59: Carousel, 7–9 slides. 'Link in bio' on the last slide. | L59: https://www.mesmatters.com/post/practical-genai-for-the-shopfloor | M59: 2 | N59: Planned
A60: 15 | B60: ='Weekly overview'!$B$16+(2) | C60: Thu | D60: Practical GenAI for the shopfloor: four uses that save time today | E60: Smart Factory & AI | F60: Question / poll | G60: Would your operators trust an AI answer on the shopfloor? | H60: • Poll: yes / only if it shows its sources / not yet / never • Comment: what would earn that trust? | I60: LinkedIn poll (1 week). Reply to comments. | J60: Poll. | K60: Story poll, plus a quote graphic in the feed. | L60: No link (keeps reach up) | M60: 3 | N60: Planned
A61: 15 | B61: ='Weekly overview'!$B$16+(3) | C61: Fri | D61: Practical GenAI for the shopfloor: four uses that save time today | E61: Smart Factory & AI | F61: Stat or framework | G61: The one condition that decides whether shopfloor GenAI works: contextualised, trusted data. | H61: • Graphic: question → data with context → answer with sources • Without the middle step, you get confident guesses | I61: Image or document carousel. No link. | J61: Single post with the image. | K61: Carousel, 5–7 slides. | L61: No link (keeps reach up) | M61: 4 | N61: Planned
A62: 16 | B62: ='Weekly overview'!$B$17+(-1) | C62: Mon | D62: WMS, MES and ERP: who owns inventory once it reaches the line? | E62: Foundations | F62: Question / poll | G62: Do you actually need a WMS? | H62: • Poll: yes, complex warehouse / ERP is enough / MES/MOM handles it / not sure • Comment: what tipped your decision? | I62: LinkedIn poll (1 week). Reply to comments. | J62: Poll. | K62: Story poll, plus a quote graphic in the feed. | L62: No link (keeps reach up) | M62: 1 | N62: Planned
A63: 16 | B63: ='Weekly overview'!$B$17+(0) | C63: Tue | D63: WMS, MES and ERP: who owns inventory once it reaches the line? | E63: Foundations | F63: Article post | G63: ERP, WMS and MES all track stock. Who owns it once it reaches the line? | H63: • ERP: financial inventory and planning • WMS: the warehouse, if it's complex enough to need one • MES/MOM: line-side and WIP, where production consumes it • The boundary that matters is the line | I63: Text post, 150–250 words. Article link in the FIRST COMMENT. | J63: Thread, 5–7 posts. Link in the last post. | K63: Carousel, 7–9 slides. 'Link in bio' on the last slide. | L63: https://www.mesmatters.com/post/wms-vs-mes-inventory | M63: 2 | N63: Planned
A64: 16 | B64: ='Weekly overview'!$B$17+(2) | C64: Thu | D64: WMS, MES and ERP: who owns inventory once it reaches the line? | E64: Foundations | F64: Stat or framework | G64: Warehouse → line-side → WIP → finished goods. Who owns each stage? | H64: • Graphic: the inventory boundary map • Carousel: one stage per slide, system of record on each | I64: Image or document carousel. No link. | J64: Single post with the image. | K64: Carousel, 5–7 slides. | L64: No link (keeps reach up) | M64: 3 | N64: Planned
A65: 16 | B65: ='Weekly overview'!$B$17+(3) | C65: Fri | D65: WMS, MES and ERP: who owns inventory once it reaches the line? | E65: Foundations | F65: Contrarian take | G65: If your WMS doesn't know what the line just consumed, you have two inventories and one is wrong. | H65: • Real-time consumption belongs to whoever sees production • Sync to ERP, don't duplicate it | I65: Short text post, 50–120 words. No link. | J65: Single post. | K65: Carousel: the take on slide 1, the reasoning over 3–4 slides. | L65: No link (keeps reach up) | M65: 4 | N65: Planned
A66: 17 | B66: ='Weekly overview'!$B$18+(-1) | C66: Mon | D66: IIoT doesn't replace MES. Here's why. | E66: Foundations | F66: Myth vs reality | G66: Myth: if we connect every machine, we won't need MES. | H66: • Reality: you'll have a lot of data and no process around it • Orders, quality, materials and people still need managing. Carousel: four IIoT myths | I66: Text post or document carousel. No link. | J66: Single post. | K66: Carousel: myth slide, reality slide. | L66: No link (keeps reach up) | M66: 1 | N66: Planned
A67: 17 | B67: ='Weekly overview'!$B$18+(0) | C67: Tue | D67: IIoT doesn't replace MES. Here's why. | E67: Foundations | F67: Article post | G67: IIoT doesn't replace MES. Here's why. | H67: • IIoT is a concept, not a system • Connecting sensors is a small part of running a factory • Collecting machine data is table stakes for MES/MOM • Complementary, not competing | I67: Text post, 150–250 words. Article link in the FIRST COMMENT. | J67: Thread, 5–7 posts. Link in the last post. | K67: Carousel, 7–9 slides. 'Link in bio' on the last slide. | L67: https://www.mesmatters.com/post/iiot-vs-mes | M67: 2 | N67: Planned
A68: 17 | B68: ='Weekly overview'!$B$18+(2) | C68: Thu | D68: IIoT doesn't replace MES. Here's why. | E68: Foundations | F68: Question / poll | G68: Have you seen an IIoT project stall after the dashboards went live? | H68: • Poll: yes / no / it's happening now / we skipped IIoT • Comment: what happened next? | I68: LinkedIn poll (1 week). Reply to comments. | J68: Poll. | K68: Story poll, plus a quote graphic in the feed. | L68: No link (keeps reach up) | M68: 3 | N68: Planned
A69: 17 | B69: ='Weekly overview'!$B$18+(3) | C69: Fri | D69: IIoT doesn't replace MES. Here's why. | E69: Foundations | F69: Analogy | G69: IIoT gives you the factory's pulse. MES/MOM tells you what the patient is doing. | H69: • A pulse alone doesn't tell you why it changed • Context comes from orders, products and people | I69: Short text post, 50–120 words. No link. | J69: Single post. | K69: Quote graphic. | L69: No link (keeps reach up) | M69: 4 | N69: Planned
A70: 18 | B70: ='Weekly overview'!$B$19+(-1) | C70: Mon | D70: Configure, don't customise | E70: Implementation | F70: Contrarian take | G70: 'Our processes are unique' is the most expensive sentence in manufacturing software. | H70: • Most are variations of best practice • The genuinely unique bits are worth protecting. The rest isn't. Challenge every requirement that starts with 'we've always' | I70: Short text post, 50–120 words. No link. | J70: Single post. | K70: Carousel: the take on slide 1, the reasoning over 3–4 slides. | L70: No link (keeps reach up) | M70: 1 | N70: Planned
A71: 18 | B71: ='Weekly overview'!$B$19+(0) | C71: Tue | D71: Configure, don't customise | E71: Implementation | F71: Article post | G71: Configuration and customisation are not the same thing. The difference decides your total cost of ownership. | H71: • Six levels, from out-of-the-box to custom code • Every custom line makes upgrades harder • Your processes probably aren't as unique as you think • One warning sign tells you it's going wrong | I71: Text post, 150–250 words. Article link in the FIRST COMMENT. | J71: Thread, 5–7 posts. Link in the last post. | K71: Carousel, 7–9 slides. 'Link in bio' on the last slide. | L71: https://www.mesmatters.com/post/configure-dont-customise | M71: 2 | N71: Planned
A72: 18 | B72: ='Weekly overview'!$B$19+(2) | C72: Thu | D72: Configure, don't customise | E72: Implementation | F72: Stat or framework | G72: Out-of-the-box → configuration → low-code → extensions → integration → customisation. | H72: • Graphic: the six levels, cost and upgrade risk rising left to right • Carousel version | I72: Image or document carousel. No link. | J72: Single post with the image. | K72: Carousel, 5–7 slides. | L72: No link (keeps reach up) | M72: 3 | N72: Planned
A73: 18 | B73: ='Weekly overview'!$B$19+(3) | C73: Fri | D73: Configure, don't customise | E73: Implementation | F73: Question / poll | G73: How much of your current MES is custom code? | H73: • Poll: almost none / some / most of it / we built it ourselves • Comment: what does an upgrade cost you? | I73: LinkedIn poll (1 week). Reply to comments. | J73: Poll. | K73: Story poll, plus a quote graphic in the feed. | L73: No link (keeps reach up) | M73: 4 | N73: Planned
A74: 19 | B74: ='Weekly overview'!$B$20+(-1) | C74: Mon | D74: ERP, APS and MES scheduling: the plan versus the shift | E74: Foundations | F74: Analogy | G74: ERP is the season plan. APS is the match tactics. MES is what happens on the pitch. | H74: • Plans change the moment the whistle blows • The shopfloor has to feed reality back | I74: Short text post, 50–120 words. No link. | J74: Single post. | K74: Quote graphic. | L74: No link (keeps reach up) | M74: 1 | N74: Planned
A75: 19 | B75: ='Weekly overview'!$B$20+(0) | C75: Tue | D75: ERP, APS and MES scheduling: the plan versus the shift | E75: Foundations | F75: Article post | G75: ERP plans. APS sequences. MES executes. Where does scheduling actually belong? | H75: • Different systems, different horizons • Many factories don't need APS at all • Where the scheduling logic should live • The feedback loop from the shopfloor is the whole point | I75: Text post, 150–250 words. Article link in the FIRST COMMENT. | J75: Thread, 5–7 posts. Link in the last post. | K75: Carousel, 7–9 slides. 'Link in bio' on the last slide. | L75: https://www.mesmatters.com/post/aps-vs-mes-scheduling | M75: 2 | N75: Planned
A76: 19 | B76: ='Weekly overview'!$B$20+(2) | C76: Thu | D76: ERP, APS and MES scheduling: the plan versus the shift | E76: Foundations | F76: Question / poll | G76: How old is your production schedule by mid-shift? | H76: • Poll: live / a few hours / since this morning / since last week • Comment: who updates it? | I76: LinkedIn poll (1 week). Reply to comments. | J76: Poll. | K76: Story poll, plus a quote graphic in the feed. | L76: No link (keeps reach up) | M76: 3 | N76: Planned
A77: 19 | B77: ='Weekly overview'!$B$20+(3) | C77: Fri | D77: ERP, APS and MES scheduling: the plan versus the shift | E77: Foundations | F77: Checklist | G77: Four questions to decide if you need APS. | H77: • Do you have many shared constraints? • Are changeovers sequence-dependent? • Does the schedule change daily? • Can planners keep up today? Carousel | I77: Document carousel (PDF), one item per page. | J77: Thread, one item per post. | K77: Carousel, one item per slide. | L77: No link (keeps reach up) | M77: 4 | N77: Planned
A78: 20 | B78: ='Weekly overview'!$B$21+(-1) | C78: Mon | D78: Digital work instructions that know what's running | E78: Smart Factory & AI | F78: Story (your experience) | G78: Story prompt: the out-of-date instruction that caused a problem. | H78: • Your experience: wrong revision, missing step, laminated sheet from 2015 • What did it cost?. End: how current are yours? | I78: Story post, 150–250 words, from your own experience. No link. | J78: Short thread, 3–4 posts. | K78: Reel: 30–45 sec talking to camera. | L78: No link (keeps reach up) | M78: 1 | N78: Planned
A79: 20 | B79: ='Weekly overview'!$B$21+(0) | C79: Tue | D79: Digital work instructions that know what's running | E79: Smart Factory & AI | F79: Article post | G79: Paper work instructions go out of date the day they're printed. | H79: • Digital should mean version-controlled and context-aware • Show the right instruction for the order that's running • New starters get it right in days, not months • Capture what your best operators know before they retire | I79: Text post, 150–250 words. Article link in the FIRST COMMENT. | J79: Thread, 5–7 posts. Link in the last post. | K79: Carousel, 7–9 slides. 'Link in bio' on the last slide. | L79: https://www.mesmatters.com/post/digital-work-instructions | M79: 2 | N79: Planned
A80: 20 | B80: ='Weekly overview'!$B$21+(2) | C80: Thu | D80: Digital work instructions that know what's running | E80: Smart Factory & AI | F80: Stat or framework | G80: The workforce numbers behind this: experienced people retiring, new starters staying for less time. | H80: • Use the tenure and skills stats from the connected worker article • Knowledge capture isn't optional any more | I80: Image or document carousel. No link. | J80: Single post with the image. | K80: Carousel, 5–7 slides. | L80: No link (keeps reach up) | M80: 3 | N80: Planned
A81: 20 | B81: ='Weekly overview'!$B$21+(3) | C81: Fri | D81: Digital work instructions that know what's running | E81: Smart Factory & AI | F81: Contrarian take | G81: A PDF on a tablet isn't a digital work instruction. | H81: • If it doesn't know which order is running, it's just paper on glass • Context is what makes it useful | I81: Short text post, 50–120 words. No link. | J81: Single post. | K81: Carousel: the take on slide 1, the reasoning over 3–4 slides. | L81: No link (keeps reach up) | M81: 4 | N81: Planned
A82: 21 | B82: ='Weekly overview'!$B$22+(-1) | C82: Mon | D82: Predictive maintenance needs data you probably aren't collecting yet | E82: Smart Factory & AI | F82: Myth vs reality | G82: Myth: buy a predictive maintenance platform and failures stop. | H82: • Reality: without failure history and context, the model has nothing to learn from • Start with accurate downtime reasons | I82: Text post or document carousel. No link. | J82: Single post. | K82: Carousel: myth slide, reality slide. | L82: No link (keeps reach up) | M82: 1 | N82: Planned
A83: 21 | B83: ='Weekly overview'!$B$22+(0) | C83: Tue | D83: Predictive maintenance needs data you probably aren't collecting yet | E83: Smart Factory & AI | F83: Article post | G83: Predictive maintenance needs data you probably aren't collecting yet. | H83: • Reactive, preventive, condition-based, then predictive • Downtime data is where it starts • Models need condition data, failure history, maintenance actions and operating context • Operators are part of it, not just engineers | I83: Text post, 150–250 words. Article link in the FIRST COMMENT. | J83: Thread, 5–7 posts. Link in the last post. | K83: Carousel, 7–9 slides. 'Link in bio' on the last slide. | L83: https://www.mesmatters.com/post/predictive-maintenance-data | M83: 2 | N83: Planned
A84: 21 | B84: ='Weekly overview'!$B$22+(2) | C84: Thu | D84: Predictive maintenance needs data you probably aren't collecting yet | E84: Smart Factory & AI | F84: Question / poll | G84: How is downtime recorded in your factory today? | H84: • Poll: automatically with reasons / automatically, no reasons / manually / not really • Comment: how accurate is it? | I84: LinkedIn poll (1 week). Reply to comments. | J84: Poll. | K84: Story poll, plus a quote graphic in the feed. | L84: No link (keeps reach up) | M84: 3 | N84: Planned
A85: 21 | B85: ='Weekly overview'!$B$22+(3) | C85: Fri | D85: Predictive maintenance needs data you probably aren't collecting yet | E85: Smart Factory & AI | F85: Contrarian take | G85: If production and maintenance argue about downtime figures, you're not ready for predictive anything. | H85: • One version of downtime, shared by both • That's the foundation every model needs | I85: Short text post, 50–120 words. No link. | J85: Single post. | K85: Carousel: the take on slide 1, the reasoning over 3–4 slides. | L85: No link (keeps reach up) | M85: 4 | N85: Planned
A86: 22 | B86: ='Weekly overview'!$B$23+(-1) | C86: Mon | D86: QMS and MES: closing the quality loop | E86: Foundations | F86: Stat or framework | G86: The quality loop: in-process check → non-conformance → CAPA → updated spec → back to the line. | H86: • Graphic: who owns each step • Carousel | I86: Image or document carousel. No link. | J86: Single post with the image. | K86: Carousel, 5–7 slides. | L86: No link (keeps reach up) | M86: 1 | N86: Planned
A87: 22 | B87: ='Weekly overview'!$B$23+(0) | C87: Tue | D87: QMS and MES: closing the quality loop | E87: Foundations | F87: Article post | G87: Enterprise QMS and MES both 'do quality'. Here's how they should divide the work. | H87: • QMS: CAPA, audits, complaints, documents • MES/MOM: in-process checks, SPC, holds at the line • Where the loop breaks • Holds must apply everywhere at once | I87: Text post, 150–250 words. Article link in the FIRST COMMENT. | J87: Thread, 5–7 posts. Link in the last post. | K87: Carousel, 7–9 slides. 'Link in bio' on the last slide. | L87: https://www.mesmatters.com/post/qms-and-mes-quality | M87: 2 | N87: Planned
A88: 22 | B88: ='Weekly overview'!$B$23+(2) | C88: Thu | D88: QMS and MES: closing the quality loop | E88: Foundations | F88: Question / poll | G88: When quality puts a batch on hold, how fast does production know? | H88: • Poll: instantly / within the hour / next shift / after it's shipped • Comment with an example | I88: LinkedIn poll (1 week). Reply to comments. | J88: Poll. | K88: Story poll, plus a quote graphic in the feed. | L88: No link (keeps reach up) | M88: 3 | N88: Planned
A89: 22 | B89: ='Weekly overview'!$B$23+(3) | C89: Fri | D89: QMS and MES: closing the quality loop | E89: Foundations | F89: Contrarian take | G89: A quality hold that lives in one system but not the others isn't a hold. It's a suggestion. | H89: • ERP, WMS and MES/MOM all need to respect it instantly • Test it before an auditor does | I89: Short text post, 50–120 words. No link. | J89: Single post. | K89: Carousel: the take on slide 1, the reasoning over 3–4 slides. | L89: No link (keeps reach up) | M89: 4 | N89: Planned
A90: 23 | B90: ='Weekly overview'!$B$24+(-1) | C90: Mon | D90: Your traceability probably isn't as good as you think | E90: Foundations | F90: Checklist | G90: The traceability test: can you answer these four questions in under 10 minutes? | H90: • Which lots went into this product? • Which products used this lot? • What were the process parameters at the time? • Which tool and operator? Carousel | I90: Document carousel (PDF), one item per page. | J90: Thread, one item per post. | K90: Carousel, one item per slide. | L90: No link (keeps reach up) | M90: 1 | N90: Planned
A91: 23 | B91: ='Weekly overview'!$B$24+(0) | C91: Tue | D91: Your traceability probably isn't as good as you think | E91: Foundations | F91: Article post | G91: Your traceability probably isn't as good as you think. | H91: • ERP batch tracking and backflushing is better than nothing • Full traceability includes the supplementary data: tools, parameters, results, people • That's what narrows a recall from a week to a few lots • A simple test tells you where you stand | I91: Text post, 150–250 words. Article link in the FIRST COMMENT. | J91: Thread, 5–7 posts. Link in the last post. | K91: Carousel, 7–9 slides. 'Link in bio' on the last slide. | L91: https://www.mesmatters.com/post/manufacturing-traceability | M91: 2 | N91: Planned
A92: 23 | B92: ='Weekly overview'!$B$24+(2) | C92: Thu | D92: Your traceability probably isn't as good as you think | E92: Foundations | F92: Question / poll | G92: How long would a recall investigation take in your factory? | H92: • Poll: minutes / hours / days / we'd recall everything to be safe • Comment honestly | I92: LinkedIn poll (1 week). Reply to comments. | J92: Poll. | K92: Story poll, plus a quote graphic in the feed. | L92: No link (keeps reach up) | M92: 3 | N92: Planned
A93: 23 | B93: ='Weekly overview'!$B$24+(3) | C93: Fri | D93: Your traceability probably isn't as good as you think | E93: Foundations | F93: Story (your experience) | G93: Story prompt: a recall or complaint where traceability made the difference. | H93: • Your experience, anonymised • How narrow could you make the scope?. End: what data would you add? | I93: Story post, 150–250 words, from your own experience. No link. | J93: Short thread, 3–4 posts. | K93: Reel: 30–45 sec talking to camera. | L93: No link (keeps reach up) | M93: 4 | N93: Planned
A94: 24 | B94: ='Weekly overview'!$B$25+(-1) | C94: Mon | D94: How to choose an MES: 12 questions to ask every vendor | E94: Implementation | F94: Contrarian take | G94: A 400-line RFP spreadsheet tells you which vendor is best at filling in spreadsheets. | H94: • Every vendor ticks 'yes' • Ask them to show your scenario, live, on their product | I94: Short text post, 50–120 words. No link. | J94: Single post. | K94: Carousel: the take on slide 1, the reasoning over 3–4 slides. | L94: No link (keeps reach up) | M94: 1 | N94: Planned
A95: 24 | B95: ='Weekly overview'!$B$25+(0) | C95: Tue | D95: How to choose an MES: 12 questions to ask every vendor | E95: Implementation | F95: Article post | G95: 12 questions to ask every MES vendor before you sign. | H95: • Technical foundation and user experience • Functional scope, and scalability • Don't write a wish list RFP • See it, don't read about it. And choose the partner, not just the product | I95: Text post, 150–250 words. Article link in the FIRST COMMENT. | J95: Thread, 5–7 posts. Link in the last post. | K95: Carousel, 7–9 slides. 'Link in bio' on the last slide. | L95: https://www.mesmatters.com/post/how-to-choose-an-mes | M95: 2 | N95: Planned
A96: 24 | B96: ='Weekly overview'!$B$25+(2) | C96: Thu | D96: How to choose an MES: 12 questions to ask every vendor | E96: Implementation | F96: Checklist | G96: Four of the 12 questions I'd never skip. | H96: • Is it one data model or several? • What's configuration vs custom code? • How do upgrades work? • Who supports it in year three? Carousel with all 12 | I96: Document carousel (PDF), one item per page. | J96: Thread, one item per post. | K96: Carousel, one item per slide. | L96: No link (keeps reach up) | M96: 3 | N96: Planned
A97: 24 | B97: ='Weekly overview'!$B$25+(3) | C97: Fri | D97: How to choose an MES: 12 questions to ask every vendor | E97: Implementation | F97: Question / poll | G97: What mattered most when you chose your MES? | H97: • Poll: functionality / price / user experience / the partner • Comment: what do you wish you'd asked? | I97: LinkedIn poll (1 week). Reply to comments. | J97: Poll. | K97: Story poll, plus a quote graphic in the feed. | L97: No link (keeps reach up) | M97: 4 | N97: Planned
A98: 25 | B98: ='Weekly overview'!$B$26+(-1) | C98: Mon | D98: SPC on the shopfloor: catch the drift before it becomes scrap | E98: Foundations | F98: Myth vs reality | G98: Myth: if parts are in spec, the process is under control. | H98: • Reality: a process can drift for hours inside the spec limits • SPC catches the trend before the scrap | I98: Text post or document carousel. No link. | J98: Single post. | K98: Carousel: myth slide, reality slide. | L98: No link (keeps reach up) | M98: 1 | N98: Planned
A99: 25 | B99: ='Weekly overview'!$B$26+(0) | C99: Tue | D99: SPC on the shopfloor: catch the drift before it becomes scrap | E99: Foundations | F99: Article post | G99: Catch the drift before it becomes scrap. SPC explained for operations leaders. | H99: • Specification limits and control limits are not the same • Control charts and the rules that matter • Cp and Cpk without the maths lecture • Why SPC belongs at the line, in MES/MOM | I99: Text post, 150–250 words. Article link in the FIRST COMMENT. | J99: Thread, 5–7 posts. Link in the last post. | K99: Carousel, 7–9 slides. 'Link in bio' on the last slide. | L99: https://www.mesmatters.com/post/spc-on-the-shopfloor | M99: 2 | N99: Planned
A100: 25 | B100: ='Weekly overview'!$B$26+(2) | C100: Thu | D100: SPC on the shopfloor: catch the drift before it becomes scrap | E100: Foundations | F100: Stat or framework | G100: Spec limits vs control limits on one chart. | H100: • Graphic: a drifting process staying in spec until it doesn't • Carousel | I100: Image or document carousel. No link. | J100: Single post with the image. | K100: Carousel, 5–7 slides. | L100: No link (keeps reach up) | M100: 3 | N100: Planned
...

Sheet Weekly overview
A1: Week | B1: Tuesday | C1: Featured article | D1: Pillar | E1: Article link | F1: Posts done (of 4)
A2: 1 | B2: ='How to use'!$B$3+0 | C2: Connected worker: why your operators need one app, not five | D2: Smart Factory & AI | E2: https://www.mesmatters.com/post/connected-worker-one-app-not-five | F2: =COUNTIFS(Calendar!$A:$A,A2,Calendar!$N:$N,"Posted")
A3: 2 | B3: ='How to use'!$B$3+7 | C3: What is a smart factory? No version number required | D3: Smart Factory & AI | E3: https://www.mesmatters.com/post/what-is-a-smart-factory | F3: =COUNTIFS(Calendar!$A:$A,A3,Calendar!$N:$N,"Posted")
A4: 3 | B4: ='How to use'!$B$3+14 | C4: AI, ML and GenAI on the shopfloor: what each one actually does | D4: Smart Factory & AI | E4: https://www.mesmatters.com/post/ai-ml-genai-on-the-shopfloor | F4: =COUNTIFS(Calendar!$A:$A,A4,Calendar!$N:$N,"Posted")
A5: 4 | B5: ='How to use'!$B$3+21 | C5: The smart manufacturing maturity model: you can't skip a level | D5: Smart Factory & AI | E5: https://www.mesmatters.com/post/smart-manufacturing-maturity-model | F5: =COUNTIFS(Calendar!$A:$A,A5,Calendar!$N:$N,"Posted")
A6: 5 | B6: ='How to use'!$B$3+28 | C6: PLM, ERP and MES: where the digital thread actually runs | D6: Foundations | E6: https://www.mesmatters.com/post/plm-erp-mes-digital-thread | F6: =COUNTIFS(Calendar!$A:$A,A6,Calendar!$N:$N,"Posted")
A7: 6 | B7: ='How to use'!$B$3+35 | C7: Shift handover is a process. Treat it like one. | D7: Smart Factory & AI | E7: https://www.mesmatters.com/post/digital-shift-handover | F7: =COUNTIFS(Calendar!$A:$A,A7,Calendar!$N:$N,"Posted")
A8: 7 | B8: ='How to use'!$B$3+42 | C8: The smart factory tech stack, system by system | D8: Foundations | E8: https://www.mesmatters.com/post/smart-factory-tech-stack | F8: =COUNTIFS(Calendar!$A:$A,A8,Calendar!$N:$N,"Posted")
A9: 8 | B9: ='How to use'!$B$3+49 | C9: MES vs MOM: why the difference matters when you buy | D9: Foundations | E9: https://www.mesmatters.com/post/mes-vs-mom | F9: =COUNTIFS(Calendar!$A:$A,A9,Calendar!$N:$N,"Posted")
A10: 9 | B10: ='How to use'!$B$3+56 | C10: EBOM, MBOM, as-built: who owns the BOM at each stage | D10: Foundations | E10: https://www.mesmatters.com/post/ebom-mbom-as-built | F10: =COUNTIFS(Calendar!$A:$A,A10,Calendar!$N:$N,"Posted")
A11: 10 | B11: ='How to use'!$B$3+63 | C11: Raw machine data is worthless. Context is what makes it useful | D11: Smart Factory & AI | E11: https://www.mesmatters.com/post/contextualised-manufacturing-data | F11: =COUNTIFS(Calendar!$A:$A,A11,Calendar!$N:$N,"Posted")
A12: 11 | B12: ='How to use'!$B$3+70 | C12: How to build an MES business case leadership will sign | D12: Implementation | E12: https://www.mesmatters.com/post/mes-business-case | F12: =COUNTIFS(Calendar!$A:$A,A12,Calendar!$N:$N,"Posted")
A13: 12 | B13: ='How to use'!$B$3+77 | C13: The biggest barriers to MES success in food manufacturing | D13: Implementation | E13: https://www.mesmatters.com/post/food-manufacturing-mes-barriers | F13: =COUNTIFS(Calendar!$A:$A,A13,Calendar!$N:$N,"Posted")
A14: 13 | B14: ='How to use'!$B$3+84 | C14: From CPQ to the shopfloor: building what the customer actually configured | D14: Foundations | E14: https://www.mesmatters.com/post/cpq-to-shopfloor | F14: =COUNTIFS(Calendar!$A:$A,A14,Calendar!$N:$N,"Posted")
A15: 14 | B15: ='How to use'!$B$3+91 | C15: Skills you can enforce, not just record | D15: Smart Factory & AI | E15: https://www.mesmatters.com/post/skills-enforcement-shopfloor | F15: =COUNTIFS(Calendar!$A:$A,A15,Calendar!$N:$N,"Posted")
A16: 15 | B16: ='How to use'!$B$3+98 | C16: Practical GenAI for the shopfloor: four uses that save time today | D16: Smart Factory & AI | E16: https://www.mesmatters.com/post/practical-genai-for-the-shopfloor | F16: =COUNTIFS(Calendar!$A:$A,A16,Calendar!$N:$N,"Posted")
A17: 16 | B17: ='How to use'!$B$3+105 | C17: WMS, MES and ERP: who owns inventory once it reaches the line? | D17: Foundations | E17: https://www.mesmatters.com/post/wms-vs-mes-inventory | F17: =COUNTIFS(Calendar!$A:$A,A17,Calendar!$N:$N,"Posted")
A18: 17 | B18: ='How to use'!$B$3+112 | C18: IIoT doesn't replace MES. Here's why. | D18: Foundations | E18: https://www.mesmatters.com/post/iiot-vs-mes | F18: =COUNTIFS(Calendar!$A:$A,A18,Calendar!$N:$N,"Posted")
A19: 18 | B19: ='How to use'!$B$3+119 | C19: Configure, don't customise | D19: Implementation | E19: https://www.mesmatters.com/post/configure-dont-customise | F19: =COUNTIFS(Calendar!$A:$A,A19,Calendar!$N:$N,"Posted")
A20: 19 | B20: ='How to use'!$B$3+126 | C20: ERP, APS and MES scheduling: the plan versus the shift | D20: Foundations | E20: https://www.mesmatters.com/post/aps-vs-mes-scheduling | F20: =COUNTIFS(Calendar!$A:$A,A20,Calendar!$N:$N,"Posted")
A21: 20 | B21: ='How to use'!$B$3+133 | C21: Digital work instructions that know what's running | D21: Smart Factory & AI | E21: https://www.mesmatters.com/post/digital-work-instructions | F21: =COUNTIFS(Calendar!$A:$A,A21,Calendar!$N:$N,"Posted")
A22: 21 | B22: ='How to use'!$B$3+140 | C22: Predictive maintenance needs data you probably aren't collecting yet | D22: Smart Factory & AI | E22: https://www.mesmatters.com/post/predictive-maintenance-data | F22: =COUNTIFS(Calendar!$A:$A,A22,Calendar!$N:$N,"Posted")
A23: 22 | B23: ='How to use'!$B$3+147 | C23: QMS and MES: closing the quality loop | D23: Foundations | E23: https://www.mesmatters.com/post/qms-and-mes-quality | F23: =COUNTIFS(Calendar!$A:$A,A23,Calendar!$N:$N,"Posted")
A24: 23 | B24: ='How to use'!$B$3+154 | C24: Your traceability probably isn't as good as you think | D24: Foundations | E24: https://www.mesmatters.com/post/manufacturing-traceability | F24: =COUNTIFS(Calendar!$A:$A,A24,Calendar!$N:$N,"Posted")
A25: 24 | B25: ='How to use'!$B$3+161 | C25: How to choose an MES: 12 questions to ask every vendor | D25: Implementation | E25: https://www.mesmatters.com/post/how-to-choose-an-mes | F25: =COUNTIFS(Calendar!$A:$A,A25,Calendar!$N:$N,"Posted")
A26: 25 | B26: ='How to use'!$B$3+168 | C26: SPC on the shopfloor: catch the drift before it becomes scrap | D26: Foundations | E26: https://www.mesmatters.com/post/spc-on-the-shopfloor | F26: =COUNTIFS(Calendar!$A:$A,A26,Calendar!$N:$N,"Posted")
A27: 26 | B27: ='How to use'!$B$3+175 | C27: AI for the frontline: copilots, shift summaries and coaching | D27: Smart Factory & AI | E27: https://www.mesmatters.com/post/ai-for-frontline-workers | F27: =COUNTIFS(Calendar!$A:$A,A27,Calendar!$N:$N,"Posted")
A28: 27 | B28: ='How to use'!$B$3+182 | C28: Eight smart manufacturing myths that refuse to die | D28: Smart Factory & AI | E28: https://www.mesmatters.com/post/smart-manufacturing-myths | F28: =COUNTIFS(Calendar!$A:$A,A28,Calendar!$N:$N,"Posted")
A29: 28 | B29: ='How to use'!$B$3+189 | C29: EAM, CMMS and MES: who owns the maintenance work order? | D29: Foundations | E29: https://www.mesmatters.com/post/eam-cmms-and-mes | F29: =COUNTIFS(Calendar!$A:$A,A29,Calendar!$N:$N,"Posted")
A30: 29 | B30: ='How to use'!$B$3+196 | C30: MES functionality: maintenance | D30: Foundations | E30: https://www.mesmatters.com/post/mes-functionality-maintenance | F30: =COUNTIFS(Calendar!$A:$A,A30,Calendar!$N:$N,"Posted")
A31: 30 | B31: ='How to use'!$B$3+203 | C31: Resistance to change is guaranteed. Plan for it. | D31: Implementation | E31: https://www.mesmatters.com/post/manufacturing-change-management | F31: =COUNTIFS(Calendar!$A:$A,A31,Calendar!$N:$N,"Posted")
A32: 31 | B32: ='How to use'!$B$3+210 | C32: LIMS and MES: getting lab results to the line before the batch moves on | D32: Foundations | E32: https://www.mesmatters.com/post/lims-and-mes | F32: =COUNTIFS(Calendar!$A:$A,A32,Calendar!$N:$N,"Posted")
A33: 32 | B33: ='How to use'!$B$3+217 | C33: Agentic AI and MCP, explained for people who run factories | D33: Smart Factory & AI | E33: https://www.mesmatters.com/post/agentic-ai-mcp-manufacturing | F33: =COUNTIFS(Calendar!$A:$A,A33,Calendar!$N:$N,"Posted")
A34: 33 | B34: ='How to use'!$B$3+224 | C34: Manufacturing KPIs beyond OEE | D34: Foundations | E34: https://www.mesmatters.com/post/manufacturing-kpis-beyond-oee | F34: =COUNTIFS(Calendar!$A:$A,A34,Calendar!$N:$N,"Posted")
A35: 34 | B35: ='How to use'!$B$3+231 | C35: Connecting MES/MOM to everything else: integration patterns that last | D35: Implementation | E35: https://www.mesmatters.com/post/isa95-integration-patterns | F35: =COUNTIFS(Calendar!$A:$A,A35,Calendar!$N:$N,"Posted")
A36: 35 | B36: ='How to use'!$B$3+238 | C36: Six technology mistakes that sink smart factory projects | D36: Implementation | E36: https://www.mesmatters.com/post/smart-factory-technology-mistakes | F36: =COUNTIFS(Calendar!$A:$A,A36,Calendar!$N:$N,"Posted")
A37: 36 | B37: ='How to use'!$B$3+245 | C37: Digital twins run on shopfloor data. MES/MOM is where it comes from | D37: Smart Factory & AI | E37: https://www.shopfloormatters.com/post/mes-and-digital-twins | F37: =COUNTIFS(Calendar!$A:$A,A37,Calendar!$N:$N,"Posted")
A38: 37 | B38: ='How to use'!$B$3+252 | C38: OT cybersecurity for MES/MOM: what operations leaders need to know | D38: Implementation | E38: https://www.mesmatters.com/post/ot-cybersecurity-for-mes | F38: =COUNTIFS(Calendar!$A:$A,A38,Calendar!$N:$N,"Posted")
A39: 38 | B39: ='How to use'!$B$3+259 | C39: OPC UA, MQTT and UNS in plain English | D39: Foundations | E39: https://www.mesmatters.com/post/opc-ua-mqtt-uns-explained | F39: =COUNTIFS(Calendar!$A:$A,A39,Calendar!$N:$N,"Posted")
A40: 39 | B40: ='How to use'!$B$3+266 | C40: Your ERP master data isn't ready for MES | D40: Implementation | E40: https://www.mesmatters.com/post/erp-master-data-for-mes | F40: =COUNTIFS(Calendar!$A:$A,A40,Calendar!$N:$N,"Posted")
A41: 40 | B41: ='How to use'!$B$3+273 | C41: MES/MOM in regulated industries: pharma, medical devices, aerospace and automotive | D41: Foundations | E41: https://www.mesmatters.com/post/mes-in-regulated-industries | F41: =COUNTIFS(Calendar!$A:$A,A41,Calendar!$N:$N,"Posted")
A42: 41 | B42: ='How to use'!$B$3+280 | C42: You can't hit ESG targets without shopfloor data | D42: Smart Factory & AI | E42: https://www.mesmatters.com/post/esg-needs-shopfloor-data | F42: =COUNTIFS(Calendar!$A:$A,A42,Calendar!$N:$N,"Posted")
A43: 42 | B43: ='How to use'!$B$3+287 | C43: MES functionality: tooling | D43: Foundations | E43: https://www.mesmatters.com/post/mes-functionality-tooling | F43: =COUNTIFS(Calendar!$A:$A,A43,Calendar!$N:$N,"Posted")
A44: 43 | B44: ='How to use'!$B$3+294 | C44: Closing the loop: service data back to the shopfloor and engineering | D44: Smart Factory & AI | E44: https://www.mesmatters.com/post/service-data-back-to-engineering | F44: =COUNTIFS(Calendar!$A:$A,A44,Calendar!$N:$N,"Posted")
A45: 44 | B45: ='How to use'!$B$3+301 | C45: Replacing a homegrown MES: the people problem nobody plans for | D45: Implementation | E45: https://www.mesmatters.com/post/replacing-a-homegrown-mes | F45: =COUNTIFS(Calendar!$A:$A,A45,Calendar!$N:$N,"Posted")
A46: 45 | B46: ='How to use'!$B$3+308 | C46: What the research says about smart factory ROI | D46: Smart Factory & AI | E46: https://www.mesmatters.com/post/smart-factory-roi-research | F46: =COUNTIFS(Calendar!$A:$A,A46,Calendar!$N:$N,"Posted")
A47: 46 | B47: ='How to use'!$B$3+315 | C47: Cloud, on-premises or hybrid: where should your MES run? | D47: Foundations | E47: https://www.mesmatters.com/post/cloud-vs-on-premises-mes | F47: =COUNTIFS(Calendar!$A:$A,A47,Calendar!$N:$N,"Posted")
A48: 47 | B48: ='How to use'!$B$3+322 | C48: How long does an MES implementation take? | D48: Implementation | E48: https://www.mesmatters.com/post/how-long-does-mes-implementation-take | F48: =COUNTIFS(Calendar!$A:$A,A48,Calendar!$N:$N,"Posted")
A49: 48 | B49: ='How to use'!$B$3+329 | C49: Going paperless: start small, but start with the end in mind | D49: Implementation | E49: https://www.mesmatters.com/post/paperless-manufacturing | F49: =COUNTIFS(Calendar!$A:$A,A49,Calendar!$N:$N,"Posted")
A50: 49 | B50: ='How to use'!$B$3+336 | C50: Discrete, process, batch or mixed-mode: why it changes your MES choice | D50: Foundations | E50: https://www.mesmatters.com/post/discrete-vs-process-manufacturing | F50: =COUNTIFS(Calendar!$A:$A,A50,Calendar!$N:$N,"Posted")
A51: 50 | B51: ='How to use'!$B$3+343 | C51: MES functionality: energy | D51: Foundations | E51: https://www.mesmatters.com/post/mes-functionality-energy | F51: =COUNTIFS(Calendar!$A:$A,A51,Calendar!$N:$N,"Posted")
A52: 51 | B52: ='How to use'!$B$3+350 | C52: Process before technology: map your as-is before you buy anything | D52: Implementation | E52: https://www.mesmatters.com/post/manufacturing-process-mapping | F52: =COUNTIFS(Calendar!$A:$A,A52,Calendar!$N:$N,"Posted")
A53: 52 | B53: ='How to use'!$B$3+357 | C53: Do you need both SCADA and MES? | D53: Foundations | E53: https://www.mesmatters.com/post/scada-vs-mes | F53: =COUNTIFS(Calendar!$A:$A,A53,Calendar!$N:$N,"Posted")
A54: 53 | B54: ='How to use'!$B$3+364 | C54: Rolling out across sites: the centre of excellence and template approach | D54: Implementation | E54: https://www.mesmatters.com/post/mes-multi-site-rollout | F54: =COUNTIFS(Calendar!$A:$A,A54,Calendar!$N:$N,"Posted")
A55: 54 | B55: ='How to use'!$B$3+371 | C55: Historians, data lakes and data fabric: where shopfloor data lives | D55: Foundations | E55: https://www.mesmatters.com/post/manufacturing-data-platforms | F55: =COUNTIFS(Calendar!$A:$A,A55,Calendar!$N:$N,"Posted")
A56: 55 | B56: ='How to use'!$B$3+378 | C56: The smart factory glossary | D56: Foundations | E56: https://www.mesmatters.com/post/smart-factory-glossary | F56: =COUNTIFS(Calendar!$A:$A,A56,Calendar!$N:$N,"Posted")
A57: 56 | B57: ='How to use'!$B$3+385 | C57: Go-live is the starting line | D57: Implementation | E57: https://www.mesmatters.com/post/mes-go-live | F57: =COUNTIFS(Calendar!$A:$A,A57,Calendar!$N:$N,"Posted")

Sheet Post types
A1: Post type | B1: What it is | C1: LinkedIn | D1: X | E1: Instagram
A2: Article post | B2: The weekly anchor. Sells the featured article and drives people to the site and newsletter. | C2: Text post, 150–250 words. Article link in the FIRST COMMENT. | D2: Thread, 5–7 posts. Link in the last post. | E2: Carousel, 7–9 slides. 'Link in bio' on the last slide.
A3: Contrarian take | B3: A sharp opinion that challenges a common belief. Starts discussion. | C3: Short text post, 50–120 words. No link. | D3: Single post. | E3: Carousel: the take on slide 1, the reasoning over 3–4 slides.
A4: Story (your experience) | B4: A real moment from your own career that illustrates the theme. You write it; the calendar gives the prompt. | C4: Story post, 150–250 words, from your own experience. No link. | D4: Short thread, 3–4 posts. | E4: Reel: 30–45 sec talking to camera.
A5: Stat or framework | B5: One number or one framework, made visual. | C5: Image or document carousel. No link. | D5: Single post with the image. | E5: Carousel, 5–7 slides.
A6: Question / poll | B6: A question or poll that invites people to share their experience. | C6: LinkedIn poll (1 week). Reply to comments. | D6: Poll. | E6: Story poll, plus a quote graphic in the feed.
A7: Myth vs reality | B7: A common belief and why it's wrong. | C7: Text post or document carousel. No link. | D7: Single post. | E7: Carousel: myth slide, reality slide.
A8: Checklist | B8: A short list people save and come back to. | C8: Document carousel (PDF), one item per page. | D8: Thread, one item per post. | E8: Carousel, one item per slide.
A9: Analogy | B9: An everyday comparison that makes a technical idea click. | C9: Short text post, 50–120 words. No link. | D9: Single post. | E9: Quote graphic.
A11: Posts per type
A12: Article post | B12: =COUNTIF(Calendar!$F:$F,A12)
A13: Contrarian take | B13: =COUNTIF(Calendar!$F:$F,A13)
A14: Story (your experience) | B14: =COUNTIF(Calendar!$F:$F,A14)
A15: Stat or framework | B15: =COUNTIF(Calendar!$F:$F,A15)
A16: Question / poll | B16: =COUNTIF(Calendar!$F:$F,A16)
A17: Myth vs reality | B17: =COUNTIF(Calendar!$F:$F,A17)
A18: Checklist | B18: =COUNTIF(Calendar!$F:$F,A18)
A19: Analogy | B19: =COUNTIF(Calendar!$F:$F,A19)
A20: Total | B20: =SUM(B12:B19)
